gwvolman/__init__.py
gwvolman/constants.py
gwvolman/fs_container.py
gwvolman/tasks.py
gwvolman/tasks_base.py
gwvolman/tasks_docker.py
gwvolman/tasks_factory.py
gwvolman/tasks_kubernetes.py
gwvolman/utils.py
gwvolman/utils_k8s.py
gwvolman/lib/__init__.py
gwvolman/lib/publish_provider.py
gwvolman/lib/stats_collector.py
gwvolman/lib/zenodo.py
gwvolman/r2d/__init__.py
gwvolman/r2d/builder.py
gwvolman/r2d/docker.py
gwvolman/r2d/kaniko.py
gwvolman/r2d/remote.py
gwvolman/remote_builder/__init__.py
gwvolman/remote_builder/server.py
gwvolman-2.1.0.dist-info/LICENSE
gwvolman-2.1.0.dist-info/METADATA
gwvolman-2.1.0.dist-info/WHEEL
gwvolman-2.1.0.dist-info/entry_points.txt
gwvolman-2.1.0.dist-info/top_level.txt
gwvolman-2.1.0.dist-info/RECORD
