Metadata-Version: 2.2
Name: gwvolman
Version: 2.1.0
Summary: WholeTale Girder Volume Manager
Author: Kacper Kowalik
Author-email: xarthisius.kk@gmail.com
License: BSD-3-Clause
Classifier: Development Status :: 2 - Pre-Alpha
Classifier: License :: OSI Approved :: BSD License
Classifier: Intended Audience :: Science/Research
Classifier: Natural Language :: English
Classifier: Programming Language :: Python
License-File: LICENSE
Requires-Dist: girder-client
Requires-Dist: girder-worker>=5.0.0a5.dev0
Requires-Dist: kubernetes
Requires-Dist: docker>=2.3.0
Requires-Dist: requests
Requires-Dist: markdown
Requires-Dist: lxml[html_clean]
Requires-Dist: pystache
Requires-Dist: celery[redis]>5
Requires-Dist: python-dateutil
Dynamic: author
Dynamic: author-email
Dynamic: classifier
Dynamic: license
Dynamic: requires-dist
Dynamic: summary
